[{"neg": 0.0, "neu": 1.0, "pos": 0.0, "compound": 0.0}, {"neg": 0.0, "neu": 1.0, "pos": 0.0, "compound": 0.0}, {"neg": 0.0, "neu": 1.0, "pos": 0.0, "compound": 0.0}, {"neg": 0.305, "neu": 0.588, "pos": 0.107, "compound": -0.903}, {"neg": 0.0, "neu": 0.809, "pos": 0.191, "compound": 0.7269}, {"neg": 0.233, "neu": 0.62, "pos": 0.147, "compound": -0.2732}, {"neg": 0.055, "neu": 0.78, "pos": 0.165, "compound": 0.7765}, {"neg": 0.195, "neu": 0.805, "pos": 0.0, "compound": -0.8047}, {"neg": 0.038, "neu": 0.664, "pos": 0.298, "compound": 0.952}, {"neg": 0.0, "neu": 1.0, "pos": 0.0, "compound": 0.0}, {"neg": 0.0, "neu": 1.0, "pos": 0.0, "compound": 0.0}, {"neg": 0.0, "neu": 1.0, "pos": 0.0, "compound": 0.0}, {"neg": 0.052, "neu": 0.827, "pos": 0.121, "compound": 0.5399}, {"neg": 0.179, "neu": 0.821, "pos": 0.0, "compound": -0.5423}, {"neg": 0.0, "neu": 0.703, "pos": 0.297, "compound": 0.5859}, {"neg": 0.151, "neu": 0.755, "pos": 0.094, "compound": -0.2944}, {"neg": 0.0, "neu": 0.931, "pos": 0.069, "compound": 0.4215}, {"neg": 0.11, "neu": 0.89, "pos": 0.0, "compound": -0.6369}, {"neg": 0.158, "neu": 0.842, "pos": 0.0, "compound": -0.4588}, {"neg": 0.082, "neu": 0.852, "pos": 0.066, "compound": -0.128}, {"neg": 0.0, "neu": 1.0, "pos": 0.0, "compound": 0.0}, {"neg": 0.0, "neu": 1.0, "pos": 0.0, "compound": 0.0}, {"neg": 0.0, "neu": 0.776, "pos": 0.224, "compound": 0.6369}, {"neg": 0.0, "neu": 0.776, "pos": 0.224, "compound": 0.6369}, {"neg": 0.08, "neu": 0.822, "pos": 0.099, "compound": 0.2023}, {"neg": 0.402, "neu": 0.598, "pos": 0.0, "compound": -0.5719}, {"neg": 0.084, "neu": 0.816, "pos": 0.1, "compound": 0.1531}, {"neg": 0.061, "neu": 0.867, "pos": 0.072, "compound": 0.1045}, {"neg": 0.124, "neu": 0.766, "pos": 0.11, "compound": -0.1111}, {"neg": 0.117, "neu": 0.836, "pos": 0.047, "compound": -0.1581}, {"neg": 0.246, "neu": 0.754, "pos": 0.0, "compound": -0.7994}, {"neg": 0.0, "neu": 0.783, "pos": 0.217, "compound": 0.9056}, {"neg": 0.0, "neu": 0.879, "pos": 0.121, "compound": 0.4404}, {"neg": 0.035, "neu": 0.892, "pos": 0.073, "compound": 0.461}, {"neg": 0.165, "neu": 0.835, "pos": 0.0, "compound": -0.4151}, {"neg": 0.131, "neu": 0.642, "pos": 0.226, "compound": 0.4767}, {"neg": 0.0, "neu": 0.683, "pos": 0.317, "compound": 0.8807}, {"neg": 0.0, "neu": 1.0, "pos": 0.0, "compound": 0.0}, {"neg": 0.0, "neu": 1.0, "pos": 0.0, "compound": 0.0}, {"neg": 0.232, "neu": 0.71, "pos": 0.058, "compound": -0.7039}, {"neg": 0.0, "neu": 1.0, "pos": 0.0, "compound": 0.0}, {"neg": 0.072, "neu": 0.928, "pos": 0.0, "compound": -0.2755}, {"neg": 0.0, "neu": 0.849, "pos": 0.151, "compound": 0.6239}, {"neg": 0.026, "neu": 0.813, "pos": 0.161, "compound": 0.8074}, {"neg": 0.0, "neu": 0.837, "pos": 0.163, "compound": 0.5719}, {"neg": 0.0, "neu": 0.78, "pos": 0.22, "compound": 0.4767}, {"neg": 0.0, "neu": 1.0, "pos": 0.0, "compound": 0.0}, {"neg": 0.152, "neu": 0.747, "pos": 0.101, "compound": -0.2869}, {"neg": 0.0, "neu": 0.789, "pos": 0.211, "compound": 0.34}, {"neg": 0.108, "neu": 0.892, "pos": 0.0, "compound": -0.6369}, {"neg": 0.0, "neu": 1.0, "pos": 0.0, "compound": 0.0}, {"neg": 0.138, "neu": 0.862, "pos": 0.0, "compound": -0.7114}, {"neg": 0.0, "neu": 1.0, "pos": 0.0, "compound": 0.0}, {"neg": 0.175, "neu": 0.825, "pos": 0.0, "compound": -0.5256}, {"neg": 0.0, "neu": 1.0, "pos": 0.0, "compound": 0.0}, {"neg": 0.115, "neu": 0.47, "pos": 0.415, "compound": 0.8256}, {"neg": 0.0, "neu": 1.0, "pos": 0.0, "compound": 0.0}, {"neg": 0.108, "neu": 0.831, "pos": 0.061, "compound": -0.2263}]